pointblank/__init__.py
pointblank/_agg.py
pointblank/_constants.py
pointblank/_constants_translations.py
pointblank/_datascan_utils.py
pointblank/_interrogation.py
pointblank/_spec_utils.py
pointblank/_typing.py
pointblank/_utils.py
pointblank/_utils_ai.py
pointblank/_utils_check_args.py
pointblank/_utils_html.py
pointblank/_utils_llms_txt.py
pointblank/actions.py
pointblank/assistant.py
pointblank/cli.py
pointblank/column.py
pointblank/compare.py
pointblank/datascan.py
pointblank/draft.py
pointblank/scan_profile.py
pointblank/scan_profile_stats.py
pointblank/schema.py
pointblank/segments.py
pointblank/thresholds.py
pointblank/validate.py
pointblank/validate.pyi
pointblank/yaml.py
pointblank/data/api-docs.txt
pointblank/data/game_revenue-duckdb.zip
pointblank/data/game_revenue.zip
pointblank/data/global_sales-duckdb.zip
pointblank/data/global_sales.zip
pointblank/data/nycflights-duckdb.zip
pointblank/data/nycflights.zip
pointblank/data/polars-api-docs.txt
pointblank/data/small_table-duckdb.zip
pointblank/data/small_table.zip
pointblank/data/validations/README.md
pointblank/data/validations/complex_preprocessing.json
pointblank/data/validations/complex_preprocessing.pkl
pointblank/data/validations/generate_test_files.py
pointblank/data/validations/multiple_steps.json
pointblank/data/validations/multiple_steps.pkl
pointblank/data/validations/narwhals_function.json
pointblank/data/validations/narwhals_function.pkl
pointblank/data/validations/no_preprocessing.json
pointblank/data/validations/no_preprocessing.pkl
pointblank/data/validations/pandas_compatible.json
pointblank/data/validations/pandas_compatible.pkl
pointblank/data/validations/preprocessing_functions.py
pointblank/data/validations/simple_preprocessing.json
pointblank/data/validations/simple_preprocessing.pkl
pointblank-0.19.0.dist-info/licenses/LICENSE
pointblank-0.19.0.dist-info/METADATA
pointblank-0.19.0.dist-info/WHEEL
pointblank-0.19.0.dist-info/entry_points.txt
pointblank-0.19.0.dist-info/top_level.txt
pointblank-0.19.0.dist-info/RECORD
