Metadata-Version: 2.4
Name: pointblank
Version: 0.19.0
Summary: Find out if your data is what you think it is.
Author-email: Richard Iannone <riannone@me.com>
License: MIT License
Project-URL: homepage, https://github.com/posit-dev/pointblank
Keywords: data,quality,validation,testing,data science,data engineering
Classifier: Development Status :: 5 - Production/Stable
Classifier: Intended Audience :: Science/Research
Classifier: License :: OSI Approved :: MIT License
Classifier: Programming Language :: Python
Classifier: Programming Language :: Python :: 3
Classifier: Programming Language :: Python :: 3.10
Classifier: Programming Language :: Python :: 3.11
Classifier: Programming Language :: Python :: 3.12
Classifier: Operating System :: OS Independent
Classifier: Topic :: Scientific/Engineering
Requires-Python: >=3.10
License-File: LICENSE
Requires-Dist: commonmark>=0.9.1
Requires-Dist: importlib-metadata
Requires-Dist: great_tables>=0.20.0
Requires-Dist: narwhals>=2.0.1
Requires-Dist: typing_extensions>=3.10.0.0
Requires-Dist: requests>=2.31.0
Requires-Dist: click>=8.0.0
Requires-Dist: rich>=13.0.0
Requires-Dist: pyyaml>=6.0.0
Provides-Extra: pd
Requires-Dist: pandas>=2.2.3; extra == "pd"
Provides-Extra: pl
Requires-Dist: polars>=1.33.0; extra == "pl"
Provides-Extra: pyspark
Requires-Dist: pyspark==3.5.6; extra == "pyspark"
Provides-Extra: generate
Requires-Dist: chatlas>=0.3.0; extra == "generate"
Requires-Dist: anthropic[bedrock]>=0.45.2; extra == "generate"
Requires-Dist: openai>=1.63.0; extra == "generate"
Requires-Dist: httpx>=0.28.0; extra == "generate"
Requires-Dist: shiny>=1.3.0; extra == "generate"
Provides-Extra: mcp
Requires-Dist: mcp[cli]>=1.10.1; extra == "mcp"
Requires-Dist: fastmcp>=2.11.3; extra == "mcp"
Requires-Dist: pytest-asyncio>=1.0.0; extra == "mcp"
Provides-Extra: excel
Requires-Dist: openpyxl>=3.0.0; extra == "excel"
Provides-Extra: bigquery
Requires-Dist: ibis-framework[bigquery]>=9.5.0; extra == "bigquery"
Provides-Extra: databricks
Requires-Dist: ibis-framework[databricks]>=9.5.0; extra == "databricks"
Provides-Extra: duckdb
Requires-Dist: ibis-framework[duckdb]>=9.5.0; extra == "duckdb"
Provides-Extra: mysql
Requires-Dist: ibis-framework[mysql]>=9.5.0; extra == "mysql"
Provides-Extra: mssql
Requires-Dist: ibis-framework[mssql]>=9.5.0; extra == "mssql"
Provides-Extra: postgres
Requires-Dist: ibis-framework[postgres]>=9.5.0; extra == "postgres"
Provides-Extra: snowflake
Requires-Dist: ibis-framework[snowflake]>=9.5.0; extra == "snowflake"
Provides-Extra: sqlite
Requires-Dist: ibis-framework[sqlite]>=9.5.0; extra == "sqlite"
Provides-Extra: docs
Requires-Dist: jupyter; extra == "docs"
Requires-Dist: nbclient>=0.10.0; extra == "docs"
Requires-Dist: nbformat>=5.10.4; extra == "docs"
Requires-Dist: quartodoc>=0.8.1; python_version >= "3.9" and extra == "docs"
Requires-Dist: pandas>=2.2.3; extra == "docs"
Requires-Dist: polars>=1.17.1; extra == "docs"
Requires-Dist: pyspark==3.5.6; extra == "docs"
Requires-Dist: openpyxl>=3.0.0; extra == "docs"
Requires-Dist: duckdb<1.3.3,>=1.2.0; extra == "docs"
Dynamic: license-file
